deplint/__init__.py
deplint/analyzers/__init__.py
deplint/analyzers/can_be_upgraded.py
deplint/analyzers/is_transitive_dep.py
deplint/analyzers/is_unused.py
deplint/analyzers/is_vulnerable.py
deplint/analyzers/required_installed.py
deplint/analyzers/required_not_installed.py
deplint/analyzers/tests/__init__.py
deplint/analyzers/tests/test_can_be_upgraded.py
deplint/analyzers/tests/test_is_transitive_dep.py
deplint/analyzers/tests/test_is_unused.py
deplint/analyzers/tests/test_is_vulnerable.py
deplint/analyzers/tests/test_required_installed.py
deplint/analyzers/tests/test_required_not_installed.py
deplint/data_sources/__init__.py
deplint/data_sources/pip.py
deplint/data_sources/site_packages/__init__.py
deplint/data_sources/site_packages/site_packages.py
deplint/data_sources/site_packages/scripts/__init__.py
deplint/data_sources/site_packages/scripts/query_installed.py
deplint/data_sources/site_packages/tests/__init__.py
deplint/data_sources/site_packages/tests/test_query_packages.py
deplint/data_sources/source_code/__init__.py
deplint/data_sources/source_code/git_grep.py
deplint/data_sources/source_code/tests/__init__.py
deplint/data_sources/source_code/tests/test_git_grep.py
deplint/data_sources/tests/__init__.py
deplint/model/__init__.py
deplint/model/advice.py
deplint/model/advice_list.py
deplint/model/available_packages.py
deplint/model/installed_packages.py
deplint/model/package_installed.py
deplint/model/package_releases.py
deplint/model/package_requirement.py
deplint/model/requirements_txt.py
deplint/model/tests/__init__.py
deplint/model/tests/test_advice.py
deplint/model/tests/test_advice_list.py
deplint/model/tests/test_available_packages.py
deplint/model/tests/test_installed_packages.py
deplint/model/tests/test_package_installed.py
deplint/model/tests/test_package_releases.py
deplint/model/tests/test_package_requirement.py
deplint/model/tests/test_requirements_txt.py
deplint/parsers/__init__.py
deplint-0.0.3.dist-info/DESCRIPTION.rst
deplint-0.0.3.dist-info/METADATA
deplint-0.0.3.dist-info/RECORD
deplint-0.0.3.dist-info/WHEEL
deplint-0.0.3.dist-info/metadata.json
deplint-0.0.3.dist-info/top_level.txt
