Metadata-Version: 2.0
Name: deplint
Version: 0.0.3
Summary: A linter for dependencies
Home-page: https://github.com/numerodix/deplint
Author: Martin Matusiak
Author-email: numerodix@gmail.com
License: Apache
Keywords: requirements dependencies linter pip
Platform: UNKNOWN
Classifier: Development Status :: 3 - Alpha
Classifier: License :: OSI Approved :: Apache Software License
Classifier: Topic :: Utilities
Classifier: Topic :: Software Development :: Quality Assurance
Classifier: Intended Audience :: Developers
Requires-Dist: packaging
Requires-Dist: safety
Requires-Dist: six
